lrdbench/__init__.py
lrdbench/analysis/__init__.py
lrdbench/analysis/advanced_metrics.py
lrdbench/analysis/auto_optimized_estimator.py
lrdbench/analysis/benchmark.py
lrdbench/analysis/high_performance/jax/__init__.py
lrdbench/analysis/high_performance/jax/cwt_jax.py
lrdbench/analysis/high_performance/jax/dfa_jax.py
lrdbench/analysis/high_performance/jax/dma_jax.py
lrdbench/analysis/high_performance/jax/gph_jax.py
lrdbench/analysis/high_performance/jax/higuchi_jax.py
lrdbench/analysis/high_performance/jax/mfdfa_jax.py
lrdbench/analysis/high_performance/jax/multifractal_wavelet_leaders_jax.py
lrdbench/analysis/high_performance/jax/periodogram_jax.py
lrdbench/analysis/high_performance/jax/rs_jax.py
lrdbench/analysis/high_performance/jax/wavelet_log_variance_jax.py
lrdbench/analysis/high_performance/jax/wavelet_variance_jax.py
lrdbench/analysis/high_performance/jax/wavelet_whittle_jax.py
lrdbench/analysis/high_performance/jax/whittle_jax.py
lrdbench/analysis/high_performance/numba/__init__.py
lrdbench/analysis/high_performance/numba/cwt_numba.py
lrdbench/analysis/high_performance/numba/dfa_numba.py
lrdbench/analysis/high_performance/numba/dma_numba.py
lrdbench/analysis/high_performance/numba/gph_numba.py
lrdbench/analysis/high_performance/numba/higuchi_numba.py
lrdbench/analysis/high_performance/numba/mfdfa_numba.py
lrdbench/analysis/high_performance/numba/multifractal_wavelet_leaders_numba.py
lrdbench/analysis/high_performance/numba/periodogram_numba.py
lrdbench/analysis/high_performance/numba/rs_numba.py
lrdbench/analysis/high_performance/numba/wavelet_log_variance_numba.py
lrdbench/analysis/high_performance/numba/wavelet_variance_numba.py
lrdbench/analysis/high_performance/numba/wavelet_whittle_numba.py
lrdbench/analysis/high_performance/numba/whittle_numba.py
lrdbench/analysis/machine_learning/__init__.py
lrdbench/analysis/machine_learning/base_ml_estimator.py
lrdbench/analysis/machine_learning/cnn_estimator.py
lrdbench-1.5.1.dist-info/licenses/LICENSE
lrdbench-1.5.1.dist-info/METADATA
lrdbench-1.5.1.dist-info/WHEEL
lrdbench-1.5.1.dist-info/entry_points.txt
lrdbench-1.5.1.dist-info/top_level.txt
lrdbench-1.5.1.dist-info/RECORD
