Metadata-Version: 2.4
Name: lrdbench
Version: 1.5.1
Summary: Long-Range Dependence Benchmarking Toolkit
Home-page: https://github.com/dave2k77/LRDBenchmark
Author: LRDBench Development Team
Author-email: LRDBench Development Team <lrdbench@example.com>
License: MIT
Project-URL: Homepage, https://github.com/dave2k77/LRDBenchmark
Project-URL: Documentation, https://lrdbench.readthedocs.io/
Project-URL: Repository, https://github.com/dave2k77/LRDBenchmark.git
Project-URL: Issues, https://github.com/dave2k77/LRDBenchmark/issues
Classifier: Development Status :: 5 - Production/Stable
Classifier: Intended Audience :: Science/Research
Classifier: Intended Audience :: Developers
Classifier: License :: OSI Approved :: MIT License
Classifier: Operating System :: OS Independent
Classifier: Programming Language :: Python :: 3
Classifier: Programming Language :: Python :: 3.8
Classifier: Programming Language :: Python :: 3.9
Classifier: Programming Language :: Python :: 3.10
Classifier: Programming Language :: Python :: 3.11
Classifier: Programming Language :: Python :: 3.12
Classifier: Topic :: Scientific/Engineering :: Mathematics
Classifier: Topic :: Scientific/Engineering :: Physics
Classifier: Topic :: Scientific/Engineering :: Information Analysis
Classifier: Topic :: Software Development :: Libraries :: Python Modules
Requires-Python: >=3.8
License-File: LICENSE
Requires-Dist: numpy>=1.21.0
Requires-Dist: scipy>=1.7.0
Requires-Dist: scikit-learn>=1.0.0
Requires-Dist: pandas>=1.3.0
Requires-Dist: torch>=1.9.0
Requires-Dist: jax>=0.3.0
Requires-Dist: jaxlib>=0.3.0
Requires-Dist: numba>=0.56.0
Requires-Dist: pywavelets>=1.3.0
Requires-Dist: matplotlib>=3.5.0
Requires-Dist: seaborn>=0.11.0
Requires-Dist: psutil>=5.8.0
Requires-Dist: networkx>=2.6.0
Provides-Extra: dev
Requires-Dist: pytest>=6.0; extra == "dev"
Requires-Dist: pytest-cov>=2.12; extra == "dev"
Requires-Dist: black>=21.0; extra == "dev"
Requires-Dist: flake8>=3.9; extra == "dev"
Requires-Dist: mypy>=0.910; extra == "dev"
Provides-Extra: docs
Requires-Dist: sphinx>=4.0; extra == "docs"
Requires-Dist: sphinx-rtd-theme>=0.5; extra == "docs"
Requires-Dist: myst-parser>=0.15; extra == "docs"
Dynamic: author
Dynamic: home-page
Dynamic: license-file
Dynamic: requires-python
